udon2-0.1.0.dist-info/METADATA
udon2-0.1.0.dist-info/RECORD
udon2-0.1.0.dist-info/top_level.txt
udon2-0.1.0.dist-info/LICENSE
udon2-0.1.0.dist-info/WHEEL
udon2.libs/libboost_python39-b6322149.so.1.74.0
udon2/constants.cpython-39-x86_64-linux-gnu.so
udon2/helpers.cpython-39-x86_64-linux-gnu.so
udon2/transform.cpython-39-x86_64-linux-gnu.so
udon2/kernels.cpython-39-x86_64-linux-gnu.so
udon2/core.cpython-39-x86_64-linux-gnu.so
udon2/__init__.py
udon2/visual/render.py
udon2/visual/utils.py
udon2/visual/templates.py
udon2/visual/__init__.py
