Metadata-Version: 2.1
Name: udon2
Version: 0.1.0
Summary: Prepare your UD trees to be served!
Home-page: https://github.com/dkalpakchi/udon2
Author: Dmytro Kalpakchi
Author-email: dmytroka@kth.se
License: UNKNOWN
Platform: UNKNOWN
Classifier: Intended Audience :: Science/Research
Classifier: Programming Language :: Python :: 3 :: Only
Classifier: Programming Language :: Python :: 3
Classifier: Programming Language :: Python :: 3.6
Classifier: Programming Language :: Python :: 3.7
Classifier: Programming Language :: Python :: 3.8
Classifier: Programming Language :: Python :: 3.9
Classifier: License :: OSI Approved :: MIT License
Classifier: Operating System :: POSIX :: Linux
Classifier: Operating System :: Microsoft :: Windows
Classifier: Topic :: Scientific/Engineering
Requires-Python: >=3.6
